goodtools/__init__.py
goodtools/tools.py
goodtools-0.3.dist-info/METADATA
goodtools-0.3.dist-info/WHEEL
goodtools-0.3.dist-info/licenses/LICENCE
goodtools-0.3.dist-info/RECORD
